intelli_gateway/__init__.py
intelli_gateway/gateway_client.py
intelli_gateway-0.0.8.dist-info/METADATA
intelli_gateway-0.0.8.dist-info/WHEEL
intelli_gateway-0.0.8.dist-info/top_level.txt
intelli_gateway-0.0.8.dist-info/RECORD
