Metadata-Version: 2.1
Name: intelli-gateway
Version: 0.0.8
Summary: Python library for utilizing services offered on the Intelli Africa SMS/Email Gateway
Home-page: https://github.com/Intelli-Africa-Solutions/intelli-gateway
Author: Intelli Africa Solutions
Author-email: ngoni.mangudya@intelliafrica.solutions
License: UNKNOWN
Project-URL: Issues, https://github.com/Intelli-Africa-Solutions/intelli-gateway/issues
Platform: UNKNOWN
Classifier: Programming Language :: Python :: 3
Classifier: License :: OSI Approved :: MIT License
Classifier: Operating System :: OS Independent
Requires-Python: >= 3.6
Requires-Dist: requests
Requires-Dist: numpy
Requires-Dist: python-magic
